rst_include/__init__.py
rst_include/__init__conf__.py
rst_include/py.typed
rst_include/rst_include.py
rst_include/rst_include_cli.py
rst_include/libs/__init__.py
rst_include/libs/lib_assemble_block.py
rst_include/libs/lib_block.py
rst_include/libs/lib_block_options.py
rst_include/libs/lib_check_files.py
rst_include/libs/lib_classes.py
rst_include/libs/lib_get_include_options.py
rst_include/libs/lib_include_file.py
rst_include/libs/lib_main.py
rst_include/libs/lib_source_line.py
rst_include/libs/lib_str.py
rst_include/libs/lib_test.py
rst_include/libs/lib_test_compare_results.py
rst_include-2.1.3.dist-info/LICENSE
rst_include-2.1.3.dist-info/METADATA
rst_include-2.1.3.dist-info/WHEEL
rst_include-2.1.3.dist-info/entry_points.txt
rst_include-2.1.3.dist-info/top_level.txt
rst_include-2.1.3.dist-info/RECORD
